Metadata-Version: 1.1
Name: python2-utmp
Version: 0.4.2
Summary: utmp/wtmp reader
Home-page: https://github.com/dimkr/python2-utmp
Author: Henning Jacobs
Author-email: henning@jacobs1.de
License: Apache License 2.0
Keywords: utmp wtmp btmp last utmpx wtmpx btmpx
Platform: UNKNOWN
Classifier: Intended Audience :: Developers
Classifier: Development Status :: 4 - Beta
Classifier: Programming Language :: Python
Classifier: Programming Language :: Python :: 2.7
Classifier: Operating System :: POSIX :: Linux
Classifier: License :: OSI Approved :: Apache Software License
